[{"title": "My Gift To You", "featured_image": "https://i.chzbgr.com/full/9059480064/h28C9C555.jpg"}, {"title": "So Unfair", "featured_image": "https://i.chzbgr.com/full/9059530496/h829ED6EB.jpg"}, {"title": "We've All Been There", "featured_image": "https://i.chzbgr.com/full/9059565312/h89FCBF27.jpg"}, {"title": "Don't Kill Me", "featured_image": "https://i.chzbgr.com/full/9059580160/h19B362E5.jpg"}, {"title": "You're Fired, You're Fired, You're Fired", "featured_image": "https://i.chzbgr.com/full/9060217088/hEB8B9CFC.jpg"}, {"title": "Guess What: Nobody Cares", "featured_image": "https://i.chzbgr.com/full/9060213760/h16FBBD49.jpg"}, {"title": "Deep Thoughts", "featured_image": "https://i.chzbgr.com/full/9060218112/h00C53759.jpg"}, {"title": "Never Forget", "featured_image": "https://i.chzbgr.com/full/9060217344/h5A7E9AAA.jpg"}, {"title": "Florida Man Antics, Now In Comic Form", "featured_image": "https://i.chzbgr.com/full/9060214016/hF66F6ECA.jpg"}, {"title": "Lost In The Sauce", "featured_image": "https://i.chzbgr.com/full/9060260864/hD98D2AFC.jpg"}, {"title": "28 Funny Memes To Lift Your Spirits", "featured_image": "https://i.chzbgr.com/full/9060261376/h65A9DA7F.jpg"}, {"title": "Yo Quiero Taco Bell", "featured_image": "https://i.chzbgr.com/full/9058371328/h4B6DC88D.jpg"}, {"title": "Pun of the Day", "featured_image": "https://i.chzbgr.com/full/9058235392/h8F6700C5.jpg"}, {"title": "Doing Great", "featured_image": "https://i.chzbgr.com/full/9058318848/h7D2A91CF.jpg"}, {"title": "It's a Bird! It's a Plane! It's...Superman With A Hipster Mustache?", "featured_image": "https://i.chzbgr.com/full/9058208256/h7F28CFE8.jpg"}, {"title": "Take A Break With These 26 Life-Saving Memes", "featured_image": "https://i.chzbgr.com/full/9058155264/hC14F7171.jpg"}, {"title": "23 Memes To Help Get Your Day Going", "featured_image": "https://i.chzbgr.com/full/9058077952/hC8541E80.jpg"}, {"title": "History Is Incredible", "featured_image": "https://i.chzbgr.com/full/9058102272/h907E2633.jpg"}, {"title": "Who Did This", "featured_image": "https://i.chzbgr.com/full/9058103552/h1C80373A.jpg"}, {"title": "Healthy Distractions", "featured_image": "https://i.chzbgr.com/full/9058122240/h05F44EBA.jpg"}, {"title": "Let's Be Realistic", "featured_image": "https://i.chzbgr.com/full/9058076928/h4FB10CDA.jpg"}, {"title": "Everyone's A Little Hypocritical", "featured_image": "https://i.chzbgr.com/full/9057035520/h6A038039.jpg"}, {"title": "Got Ya", "featured_image": "https://i.chzbgr.com/full/9057036032/h9DBC2B1C.jpg"}, {"title": "22 Web Comics That Will Brighten Your Day", "featured_image": "https://i.chzbgr.com/full/9058109184/h6CF783C8.jpg"}, {"title": "Time Sure Does Fly", "featured_image": "https://i.chzbgr.com/full/9057035776/hC4D66810.jpg"}, {"title": "Feline PTSD", "featured_image": "https://i.chzbgr.com/full/9057116160/hF66C0C6A.jpg"}, {"title": "Wow", "featured_image": "https://i.chzbgr.com/full/9057131776/h63C47A89.jpg"}, {"title": "Nice Try", "featured_image": "https://i.chzbgr.com/full/9057125376/h6FC9CABF.jpg"}, {"title": "Danger Zone", "featured_image": "https://i.chzbgr.com/full/9057112320/hA2B792A9.jpg"}, {"title": "Finally, Someone Willing To Speak The Truth", "featured_image": "https://i.chzbgr.com/full/9057558016/h4012CFFA.jpg"}]