[{"title": "Classic Dad", "featured_image": "https://i.chzbgr.com/full/9210096640/hAFFC8964.jpg"}, {"title": "C'mon Mom!", "featured_image": "https://i.chzbgr.com/full/9210508032/h155C364B.jpg"}, {"title": "17 Cheating Victims Share How They Found Out They'd Been Betrayed", "featured_image": "https://i.chzbgr.com/full/9210378240/hF4930E95.jpg"}, {"title": "My Spirit Animal", "featured_image": "https://i.chzbgr.com/full/9210400000/h5A9EFE0F.jpg"}, {"title": "17 Best 'You Know I Had To Do It To Em' Memes", "featured_image": "https://i.chzbgr.com/full/9210261760/hEB6DF92D.jpg"}, {"title": "Nike's Ad Campaign With Colin Kaepernick Has The Internet Reacting In All Sorts Of Ways", "featured_image": "https://i.chzbgr.com/full/9210425088/h1399C4A8.jpg"}, {"title": "So Emotional", "featured_image": "https://i.chzbgr.com/full/9210433280/h30896E72.jpg"}, {"title": "This Fresh Star Wars Meme Is All About Destruction & Fake Solutions", "featured_image": "https://i.chzbgr.com/full/9210420736/h7783B406.jpg"}, {"title": "17 Customer Service Employees Reveal What Really Grinds Their Gears", "featured_image": "https://i.chzbgr.com/full/9167199744/hCCFAEA0C.jpg"}, {"title": "15 Amazon Memes That'll Cover All Your Bezos", "featured_image": "https://i.chzbgr.com/full/9209385728/hE5D9E539.jpg"}, {"title": "22 Funny Memes & Tweets That'll Keep You Distracted", "featured_image": "https://i.chzbgr.com/full/9209692928/h51C91111.jpg"}, {"title": "12 Horrid First-Date Stories That'll Make You Want To Be Single Forever", "featured_image": "https://i.chzbgr.com/full/9208439296/h41C28A52.jpg"}, {"title": "Over My Dead Body", "featured_image": "https://i.chzbgr.com/full/9209390848/h1E2B7894.jpg"}, {"title": "That'll Show 'Em", "featured_image": "https://i.chzbgr.com/full/9208922624/h7708961E.jpg"}, {"title": "I Need To Stop Doing That", "featured_image": "https://i.chzbgr.com/full/9208923136/hC5A03EA1.jpg"}, {"title": "22 Basic Memes That Are, Like, Too Relatable", "featured_image": "https://i.chzbgr.com/full/9208811008/h89622548.jpg"}, {"title": "HOW DID YOU KNOW HUMAN", "featured_image": "https://i.chzbgr.com/full/9208924416/h23341872.jpg"}, {"title": "Just. Stop.", "featured_image": "https://i.chzbgr.com/full/9209278720/h6994981B.jpg"}, {"title": "Girl Loses Her Friend's Beloved Pet Praying Mantis, Chaos Ensues", "featured_image": "https://i.chzbgr.com/full/9183874816/h1635DF1A.jpg"}, {"title": "35 Funny Memes To Help You Kick Back And Relax", "featured_image": "https://i.chzbgr.com/full/9185849344/hCF6B864B.jpg"}, {"title": "30 Marvelous Memes To Help You Celebrate The Weekend", "featured_image": "https://i.chzbgr.com/full/9209263104/h50BA4AFA.jpg"}, {"title": "Brace Yourself", "featured_image": "https://i.chzbgr.com/full/9209207040/hE8AA28D2.jpg"}, {"title": "Press 'F' For Respect", "featured_image": "https://i.chzbgr.com/full/9209250304/h2C08AAC1.jpg"}, {"title": "Jamming: Not Even Once", "featured_image": "https://i.chzbgr.com/full/9209267712/h9A5A191E.jpg"}, {"title": "29 Amusing Memes That'll Have You LOLlin'", "featured_image": "https://i.chzbgr.com/full/9208936448/h916D9252.jpg"}, {"title": "*Groan*", "featured_image": "https://i.chzbgr.com/full/9208758528/h9B2D6DD0.jpg"}, {"title": "27 Random Memes To Help You Ignore The Real World", "featured_image": "https://i.chzbgr.com/full/9209321728/h97B27293.jpg"}, {"title": "Hot Take!", "featured_image": "https://i.chzbgr.com/full/9208540672/h44B94E67.jpg"}, {"title": "15 Pics & Gifs Of People Absolutely Dying Inside", "featured_image": "https://i.chzbgr.com/full/9209395712/h440234B1.jpg"}, {"title": "Artist Sketches Monumentally Awful Profile Pics Of People And The Results Are Funny AF", "featured_image": "https://i.chzbgr.com/full/9208975616/h60310074.jpg"}]