[{"title": "Ooops", "featured_image": "https://i.chzbgr.com/full/8989034752/hD8B45E51.jpg"}, {"title": "Announcement:", "featured_image": "https://i.chzbgr.com/full/8989035008/h93AE0E42.jpg"}, {"title": "Why Hasn't Anyone Texted Me Back?", "featured_image": "https://i.chzbgr.com/full/8989035776/hC73C533B.jpg"}, {"title": "Uh Oh", "featured_image": "https://i.chzbgr.com/full/8989038848/hA47C69B2.jpg"}, {"title": "If You Say So, Pepsi", "featured_image": "https://i.chzbgr.com/full/8989036544/hC24F60B3.jpg"}, {"title": "And That'll Help Him... How?", "featured_image": "https://i.chzbgr.com/full/8989040384/hA66A039C.jpg"}, {"title": "They Don't Even Bother Putting a Sign Up", "featured_image": "https://i.chzbgr.com/full/8989041408/h7EBA59F6.jpg"}, {"title": "Well It IS, Fam", "featured_image": "https://i.chzbgr.com/full/8989040128/hBCE27CD0.jpg"}, {"title": "The Simpsons Saw This Coming", "featured_image": "https://i.chzbgr.com/full/8989253888/h71BCBC0B.jpg"}, {"title": "An Artist Inserted Pop Culture Into Thrift Store Paintings to Make Beautifully Modern Works of Art", "featured_image": "https://i.chzbgr.com/full/8987732224/h7E041EF8.jpg"}, {"title": "Okay Well, Nothing is Sacred", "featured_image": "https://i.chzbgr.com/full/8989246464/hFCAB86F5.jpg"}, {"title": "What a World We Live In", "featured_image": "https://i.chzbgr.com/full/8989242368/h7DD177C7.jpg"}, {"title": "You're Hired", "featured_image": "https://i.chzbgr.com/full/8989246720/h9FC67DC0.jpg"}, {"title": "Everytime You Think He's Gone, Dat Boi Comes Back for One Last Song", "featured_image": "https://i.chzbgr.com/full/8989245952/h27AEAE3F.jpg"}, {"title": "Meme of the Day: Contestant Brings the Internet to Jeopardy! ", "featured_image": "https://i.chzbgr.com/full/8989143040/h2C21DB5F.jpg"}, {"title": "Awkward Interactions as Trump Prepares to Become President Have Given Rise to Plenty of Memes", "featured_image": "https://i.chzbgr.com/full/8989165568/h1FB8F45B.jpg"}, {"title": "The Internet Really Messed With Darth Vader's Image When They Photoshopped This Still From the Rogue One Trailer", "featured_image": "https://i.chzbgr.com/full/8989212672/h55326F75.jpg"}, {"title": "That's Asking  a Lot", "featured_image": "https://i.chzbgr.com/full/8989231104/h9706250D.jpg"}, {"title": "Gotta Be Comfortable", "featured_image": "https://i.chzbgr.com/full/8989231616/h64288720.jpg"}, {"title": "With Great Buns Comes Great Responsibility?", "featured_image": "https://i.chzbgr.com/full/8989232896/h2A2CFBF7.jpg"}, {"title": "It Just Might Work", "featured_image": "https://i.chzbgr.com/full/8989231872/hEE9E8BD4.jpg"}, {"title": "Well...", "featured_image": "https://i.chzbgr.com/full/8989236992/h39516E23.jpg"}, {"title": "You're Welcome", "featured_image": "https://i.chzbgr.com/full/8989241600/h596C3363.jpg"}, {"title": "Such a Great Role Model for Young Women", "featured_image": "https://i.chzbgr.com/full/8989248256/h0162F8CB.jpg"}, {"title": "Celebrities Eating Things Will Be Your New Favorite Weird Instagram Account", "featured_image": "https://i.chzbgr.com/full/8989261312/h39FDA51A.jpg"}, {"title": "When Siri Finds Out", "featured_image": "https://i.chzbgr.com/full/8989248512/hCD6CBB61.jpg"}, {"title": "This Dad Photoshopped His Son Into Amazing and Surreal Photos", "featured_image": "https://i.chzbgr.com/full/8989256192/hE65F8961.jpg"}, {"title": "Uh...", "featured_image": "https://i.chzbgr.com/full/8989249792/hFBDFB6C3.jpg"}, {"title": "Great Idea", "featured_image": "https://i.chzbgr.com/full/8989267968/h7394346E.jpg"}, {"title": "The Internet Has Gotten Way More Advanced", "featured_image": "https://i.chzbgr.com/full/8989268736/h0B5B1E1A.jpg"}]